mondip/__init__.py
mondip/main.py
mondip-1.0.0.dist-info/METADATA
mondip-1.0.0.dist-info/WHEEL
mondip-1.0.0.dist-info/top_level.txt
mondip-1.0.0.dist-info/RECORD
