Metadata-Version: 2.1
Name: mondip
Version: 1.0.0
Requires-Dist: numpy
Requires-Dist: pandas
Requires-Dist: matplotlib
Requires-Dist: scikit-learn
